MANIFEST.in
README.md
setup.py
tdl_modify
tdl_report
tdl_set
ComplexTDL/CurrentPath.py
ComplexTDL/README.md
ComplexTDL/README_CN.md
ComplexTDL/Report.py
ComplexTDL/Settings.py
ComplexTDL/Task.py
ComplexTDL/WorkType.txt
ComplexTDL/__init__.py
ComplexTDL/db.json
ComplexTDL/number.txt
ComplexTDL/sysXXt.py
ComplexTDL.egg-info/PKG-INFO
ComplexTDL.egg-info/SOURCES.txt
ComplexTDL.egg-info/dependency_links.txt
ComplexTDL.egg-info/requires.txt
ComplexTDL.egg-info/top_level.txt