Metadata-Version: 2.1
Name: ComplexTDL
Version: 1.0.4
Summary: A complex to do list tool
Home-page: https://github.com/maquedexiju/ComplexTDL
Author: Antony Xu
Author-email: xiaoxu1993ha@126.com
License: UNKNOWN
Platform: any
